setup.cfg
setup.py
VirtualHost/__init__.py
VirtualHost/vhost.py
VirtualHost.egg-info/PKG-INFO
VirtualHost.egg-info/SOURCES.txt
VirtualHost.egg-info/dependency_links.txt
VirtualHost.egg-info/entry_points.txt
VirtualHost.egg-info/requires.txt
VirtualHost.egg-info/top_level.txt