Metadata-Version: 1.0
Name: VirtualHost
Version: 0.0.2
Summary: Apache(linux) virtual host creator
Home-page: https://github.com/porimol/vhost
Author: P.C ROY
Author-email: p.c_roy@yahoo.com
License: MIT
Keywords: vhost,virtual host
Platform: UNKNOWN
